{
  "importData": {
    "AFG": 0.016666666666666666,
    "BRB": 0.016666666666666666,
    "ZAF": 0.03333333333333333,
    "VEN": 0.016666666666666666,
    "STP": 0.016666666666666666,
    "BRA": 0.016666666666666666,
    "DMA": 0.016666666666666666,
    "VCT": 0.016666666666666666,
    "BGD": 0.016666666666666666,
    "ATG": 0.016666666666666666,
    "TTO": 0.016666666666666666,
    "LCA": 0.016666666666666666,
    "CAN": 0.03333333333333333,
    "PER": 0.016666666666666666,
    "IND": 0.05,
    "ARG": 0.016666666666666666,
    "PSE": 0.08333333333333333,
    "HTI": 0.016666666666666666,
    "PAK": 0.05,
    "JAM": 0.016666666666666666,
    "VIR": 0.016666666666666666,
    "RUS": 0.03333333333333333,
    "PHL": 0.016666666666666666,
    "DOM": 0.016666666666666666,
    "FRA": 0.03333333333333333,
    "IRN": 0.016666666666666666,
    "BHS": 0.016666666666666666,
    "UKR": 0.06666666666666667,
    "KNA": 0.016666666666666666,
    "SAU": 0.05,
    "GRD": 0.016666666666666666,
    "CHN": 0.05,
    "ISR": 0.08333333333333333,
    "PRI": 0.016666666666666666,
    "CUB": 0.016666666666666666,
    "SYR": 0.03333333333333333
  },
  "exportData": {
    "USA": 1.0
  },
  "nerData": {
    "USA": 1.0
  },
  "TopEntitiesByCountry": {
    "VEN": [
      {
        "entity": "Alien Enemies Act",
        "count": 1,
        "share": 0.5
      },
      {
        "entity": "Saudi",
        "count": 1,
        "share": 0.5
      }
    ],
    "SYR": [
      {
        "entity": "Saudi",
        "count": 2,
        "share": 0.5
      },
      {
        "entity": "Alien Enemies Act",
        "count": 1,
        "share": 0.25
      },
      {
        "entity": "Donald Trump",
        "count": 1,
        "share": 0.25
      }
    ],
    "ISR": [
      {
        "entity": "Hamas",
        "count": 3,
        "share": 0.3333333333333333
      },
      {
        "entity": "Edan Alexander",
        "count": 2,
        "share": 0.2222222222222222
      },
      {
        "entity": "Latin American",
        "count": 2,
        "share": 0.2222222222222222
      },
      {
        "entity": "Muhammad Sinwar",
        "count": 1,
        "share": 0.1111111111111111
      },
      {
        "entity": "Donald Trump",
        "count": 1,
        "share": 0.1111111111111111
      }
    ],
    "PSE": [
      {
        "entity": "Hamas",
        "count": 3,
        "share": 0.23076923076923078
      },
      {
        "entity": "Donald Trump",
        "count": 2,
        "share": 0.15384615384615385
      },
      {
        "entity": "Edan Alexander",
        "count": 2,
        "share": 0.15384615384615385
      },
      {
        "entity": "Latin American",
        "count": 2,
        "share": 0.15384615384615385
      },
      {
        "entity": "Muhammad Sinwar",
        "count": 1,
        "share": 0.07692307692307693
      },
      {
        "entity": "Afrikaners",
        "count": 1,
        "share": 0.07692307692307693
      },
      {
        "entity": "Pope Leo Xiv",
        "count": 1,
        "share": 0.07692307692307693
      },
      {
        "entity": "Francis",
        "count": 1,
        "share": 0.07692307692307693
      }
    ],
    "UKR": [
      {
        "entity": "Pope Leo Xiv",
        "count": 3,
        "share": 0.2727272727272727
      },
      {
        "entity": "Volodymyr Zelensky",
        "count": 2,
        "share": 0.18181818181818182
      },
      {
        "entity": "Donald Trump",
        "count": 2,
        "share": 0.18181818181818182
      },
      {
        "entity": "Vladimir Putin",
        "count": 1,
        "share": 0.09090909090909091
      },
      {
        "entity": "Vladimir V",
        "count": 1,
        "share": 0.09090909090909091
      },
      {
        "entity": "European",
        "count": 1,
        "share": 0.09090909090909091
      },
      {
        "entity": "Francis",
        "count": 1,
        "share": 0.09090909090909091
      }
    ],
    "RUS": [
      {
        "entity": "Volodymyr Zelensky",
        "count": 2,
        "share": 0.2857142857142857
      },
      {
        "entity": "Donald Trump",
        "count": 2,
        "share": 0.2857142857142857
      },
      {
        "entity": "Vladimir Putin",
        "count": 1,
        "share": 0.14285714285714285
      },
      {
        "entity": "Vladimir V",
        "count": 1,
        "share": 0.14285714285714285
      },
      {
        "entity": "European",
        "count": 1,
        "share": 0.14285714285714285
      }
    ],
    "CAN": [
      {
        "entity": "Donald Trump",
        "count": 2,
        "share": 0.6666666666666666
      },
      {
        "entity": "Honda",
        "count": 1,
        "share": 0.3333333333333333
      }
    ],
    "FRA": [
      {
        "entity": "Kim Kardashian",
        "count": 1,
        "share": 1.0
      }
    ],
    "SAU": [
      {
        "entity": "Donald Trump",
        "count": 4,
        "share": 0.5
      },
      {
        "entity": "Saudi",
        "count": 3,
        "share": 0.375
      },
      {
        "entity": "Middle East Tour",
        "count": 1,
        "share": 0.125
      }
    ],
    "CHN": [
      {
        "entity": "Lu",
        "count": 1,
        "share": 0.2
      },
      {
        "entity": "Donald Trump",
        "count": 1,
        "share": 0.2
      },
      {
        "entity": "Luiz In\u00e1cio Lula Da Silva",
        "count": 1,
        "share": 0.2
      },
      {
        "entity": "Xi Jinping",
        "count": 1,
        "share": 0.2
      },
      {
        "entity": "Latin American",
        "count": 1,
        "share": 0.2
      }
    ],
    "IRN": [
      {
        "entity": "Latin American",
        "count": 1,
        "share": 1.0
      }
    ],
    "PAK": [
      {
        "entity": "Donald Trump",
        "count": 2,
        "share": 1.0
      }
    ],
    "IND": [
      {
        "entity": "Donald Trump",
        "count": 2,
        "share": 1.0
      }
    ],
    "AFG": [
      {
        "entity": "Donald Trump",
        "count": 1,
        "share": 1.0
      }
    ],
    "ZAF": [
      {
        "entity": "Donald Trump",
        "count": 2,
        "share": 1.0
      }
    ],
    "ARG": [
      {
        "entity": "Nazi",
        "count": 1,
        "share": 0.5
      },
      {
        "entity": "World War II",
        "count": 1,
        "share": 0.5
      }
    ],
    "PER": [
      {
        "entity": "Pope Leo Xiv",
        "count": 2,
        "share": 0.6666666666666666
      },
      {
        "entity": "Pope",
        "count": 1,
        "share": 0.3333333333333333
      }
    ],
    "LCA": [
      {
        "entity": "Lu",
        "count": 1,
        "share": 0.2
      },
      {
        "entity": "Donald Trump",
        "count": 1,
        "share": 0.2
      },
      {
        "entity": "Luiz In\u00e1cio Lula Da Silva",
        "count": 1,
        "share": 0.2
      },
      {
        "entity": "Xi Jinping",
        "count": 1,
        "share": 0.2
      },
      {
        "entity": "Latin American",
        "count": 1,
        "share": 0.2
      }
    ],
    "BRB": [
      {
        "entity": "Lu",
        "count": 1,
        "share": 0.2
      },
      {
        "entity": "Donald Trump",
        "count": 1,
        "share": 0.2
      },
      {
        "entity": "Luiz In\u00e1cio Lula Da Silva",
        "count": 1,
        "share": 0.2
      },
      {
        "entity": "Xi Jinping",
        "count": 1,
        "share": 0.2
      },
      {
        "entity": "Latin American",
        "count": 1,
        "share": 0.2
      }
    ],
    "DOM": [
      {
        "entity": "Lu",
        "count": 1,
        "share": 0.2
      },
      {
        "entity": "Donald Trump",
        "count": 1,
        "share": 0.2
      },
      {
        "entity": "Luiz In\u00e1cio Lula Da Silva",
        "count": 1,
        "share": 0.2
      },
      {
        "entity": "Xi Jinping",
        "count": 1,
        "share": 0.2
      },
      {
        "entity": "Latin American",
        "count": 1,
        "share": 0.2
      }
    ],
    "BRA": [
      {
        "entity": "Lu",
        "count": 1,
        "share": 0.2
      },
      {
        "entity": "Donald Trump",
        "count": 1,
        "share": 0.2
      },
      {
        "entity": "Luiz In\u00e1cio Lula Da Silva",
        "count": 1,
        "share": 0.2
      },
      {
        "entity": "Xi Jinping",
        "count": 1,
        "share": 0.2
      },
      {
        "entity": "Latin American",
        "count": 1,
        "share": 0.2
      }
    ],
    "GRD": [
      {
        "entity": "Lu",
        "count": 1,
        "share": 0.2
      },
      {
        "entity": "Donald Trump",
        "count": 1,
        "share": 0.2
      },
      {
        "entity": "Luiz In\u00e1cio Lula Da Silva",
        "count": 1,
        "share": 0.2
      },
      {
        "entity": "Xi Jinping",
        "count": 1,
        "share": 0.2
      },
      {
        "entity": "Latin American",
        "count": 1,
        "share": 0.2
      }
    ],
    "DMA": [
      {
        "entity": "Lu",
        "count": 1,
        "share": 0.2
      },
      {
        "entity": "Donald Trump",
        "count": 1,
        "share": 0.2
      },
      {
        "entity": "Luiz In\u00e1cio Lula Da Silva",
        "count": 1,
        "share": 0.2
      },
      {
        "entity": "Xi Jinping",
        "count": 1,
        "share": 0.2
      },
      {
        "entity": "Latin American",
        "count": 1,
        "share": 0.2
      }
    ],
    "PRI": [
      {
        "entity": "Lu",
        "count": 1,
        "share": 0.2
      },
      {
        "entity": "Donald Trump",
        "count": 1,
        "share": 0.2
      },
      {
        "entity": "Luiz In\u00e1cio Lula Da Silva",
        "count": 1,
        "share": 0.2
      },
      {
        "entity": "Xi Jinping",
        "count": 1,
        "share": 0.2
      },
      {
        "entity": "Latin American",
        "count": 1,
        "share": 0.2
      }
    ],
    "ATG": [
      {
        "entity": "Lu",
        "count": 1,
        "share": 0.2
      },
      {
        "entity": "Donald Trump",
        "count": 1,
        "share": 0.2
      },
      {
        "entity": "Luiz In\u00e1cio Lula Da Silva",
        "count": 1,
        "share": 0.2
      },
      {
        "entity": "Xi Jinping",
        "count": 1,
        "share": 0.2
      },
      {
        "entity": "Latin American",
        "count": 1,
        "share": 0.2
      }
    ],
    "HTI": [
      {
        "entity": "Lu",
        "count": 1,
        "share": 0.2
      },
      {
        "entity": "Donald Trump",
        "count": 1,
        "share": 0.2
      },
      {
        "entity": "Luiz In\u00e1cio Lula Da Silva",
        "count": 1,
        "share": 0.2
      },
      {
        "entity": "Xi Jinping",
        "count": 1,
        "share": 0.2
      },
      {
        "entity": "Latin American",
        "count": 1,
        "share": 0.2
      }
    ],
    "JAM": [
      {
        "entity": "Lu",
        "count": 1,
        "share": 0.2
      },
      {
        "entity": "Donald Trump",
        "count": 1,
        "share": 0.2
      },
      {
        "entity": "Luiz In\u00e1cio Lula Da Silva",
        "count": 1,
        "share": 0.2
      },
      {
        "entity": "Xi Jinping",
        "count": 1,
        "share": 0.2
      },
      {
        "entity": "Latin American",
        "count": 1,
        "share": 0.2
      }
    ],
    "KNA": [
      {
        "entity": "Lu",
        "count": 1,
        "share": 0.2
      },
      {
        "entity": "Donald Trump",
        "count": 1,
        "share": 0.2
      },
      {
        "entity": "Luiz In\u00e1cio Lula Da Silva",
        "count": 1,
        "share": 0.2
      },
      {
        "entity": "Xi Jinping",
        "count": 1,
        "share": 0.2
      },
      {
        "entity": "Latin American",
        "count": 1,
        "share": 0.2
      }
    ],
    "BHS": [
      {
        "entity": "Lu",
        "count": 1,
        "share": 0.2
      },
      {
        "entity": "Donald Trump",
        "count": 1,
        "share": 0.2
      },
      {
        "entity": "Luiz In\u00e1cio Lula Da Silva",
        "count": 1,
        "share": 0.2
      },
      {
        "entity": "Xi Jinping",
        "count": 1,
        "share": 0.2
      },
      {
        "entity": "Latin American",
        "count": 1,
        "share": 0.2
      }
    ],
    "VCT": [
      {
        "entity": "Lu",
        "count": 1,
        "share": 0.2
      },
      {
        "entity": "Donald Trump",
        "count": 1,
        "share": 0.2
      },
      {
        "entity": "Luiz In\u00e1cio Lula Da Silva",
        "count": 1,
        "share": 0.2
      },
      {
        "entity": "Xi Jinping",
        "count": 1,
        "share": 0.2
      },
      {
        "entity": "Latin American",
        "count": 1,
        "share": 0.2
      }
    ],
    "TTO": [
      {
        "entity": "Lu",
        "count": 1,
        "share": 0.2
      },
      {
        "entity": "Donald Trump",
        "count": 1,
        "share": 0.2
      },
      {
        "entity": "Luiz In\u00e1cio Lula Da Silva",
        "count": 1,
        "share": 0.2
      },
      {
        "entity": "Xi Jinping",
        "count": 1,
        "share": 0.2
      },
      {
        "entity": "Latin American",
        "count": 1,
        "share": 0.2
      }
    ],
    "CUB": [
      {
        "entity": "Lu",
        "count": 1,
        "share": 0.2
      },
      {
        "entity": "Donald Trump",
        "count": 1,
        "share": 0.2
      },
      {
        "entity": "Luiz In\u00e1cio Lula Da Silva",
        "count": 1,
        "share": 0.2
      },
      {
        "entity": "Xi Jinping",
        "count": 1,
        "share": 0.2
      },
      {
        "entity": "Latin American",
        "count": 1,
        "share": 0.2
      }
    ],
    "VIR": [
      {
        "entity": "Lu",
        "count": 1,
        "share": 0.2
      },
      {
        "entity": "Donald Trump",
        "count": 1,
        "share": 0.2
      },
      {
        "entity": "Luiz In\u00e1cio Lula Da Silva",
        "count": 1,
        "share": 0.2
      },
      {
        "entity": "Xi Jinping",
        "count": 1,
        "share": 0.2
      },
      {
        "entity": "Latin American",
        "count": 1,
        "share": 0.2
      }
    ],
    "PHL": [
      {
        "entity": "Rodrigo Duterte",
        "count": 1,
        "share": 1.0
      }
    ],
    "STP": [
      {
        "entity": "Pope Leo Xiv",
        "count": 1,
        "share": 0.5
      },
      {
        "entity": "Francis",
        "count": 1,
        "share": 0.5
      }
    ],
    "BGD": [
      {
        "entity": "Political Party of",
        "count": 1,
        "share": 0.5
      },
      {
        "entity": "Hasina",
        "count": 1,
        "share": 0.5
      }
    ]
  },
  "topNer": "Donald Trump"
}